{
  "the-four-horsemen": {
    "id": 2492,
    "name": "Four Horsemen",
    "city": "Brooklyn, NY",
    "drop_time": "07:00",
    "days_advance": 29,
    "timezone": "America/New_York",
    "slot_interval": 30
  },
  "carbone": {
    "id": 6194,
    "name": "Carbone",
    "city": "New York, NY",
    "drop_time": "10:00",
    "days_advance": 29,
    "timezone": "America/New_York",
    "slot_interval": 30
  },
  "lilia": {
    "id": 418,
    "name": "Lilia",
    "city": "Brooklyn, NY",
    "drop_time": "09:00",
    "days_advance": 30,
    "timezone": "America/New_York",
    "slot_interval": 30
  },
  "don-angie": {
    "id": 25973,
    "name": "Don Angie",
    "city": "New York, NY",
    "drop_time": "09:00",
    "days_advance": 30,
    "timezone": "America/New_York",
    "slot_interval": 30
  },
  "i-sodi": {
    "id": 443,
    "name": "I Sodi",
    "city": "New York, NY",
    "drop_time": "12:00",
    "days_advance": 28,
    "timezone": "America/New_York",
    "slot_interval": 30
  },
  "golden-diner": {
    "id": 9520,
    "name": "Golden Diner",
    "city": "New York, NY",
    "drop_time": "09:00",
    "days_advance": 30,
    "timezone": "America/New_York",
    "slot_interval": 30
  },
  "4-charles-prime-rib": {
    "id": 834,
    "name": "4 Charles Prime Rib",
    "city": "Unknown",
    "drop_time": "09:00",
    "days_advance": 21,
    "timezone": "America/New_York",
    "slot_interval": 30
  }
}